.gitignore
MANIFEST.in
setup.py
eureka_client/__init__.py
eureka_client/client.py
eureka_client/ec2metadata.py
eureka_client/requests.py
eureka_client.egg-info/PKG-INFO
eureka_client.egg-info/SOURCES.txt
eureka_client.egg-info/dependency_links.txt
eureka_client.egg-info/not-zip-safe
eureka_client.egg-info/requires.txt
eureka_client.egg-info/top_level.txt