Metadata-Version: 1.0
Name: eureka-client
Version: 0.6.2
Summary: A python interface for Netflix Eureka
Home-page: UNKNOWN
Author: Jorge Dias
Author-email: jorge@mrdias.com
License: UNKNOWN
Platform: UNKNOWN
